<keymap version="1" name="IntelliJ IDEA Classic copy" parent="Mac OS X">
  <action id="Diff.FocusOppositePane" />
  <action id="NextEditorTab">
    <keyboard-shortcut first-keystroke="ctrl tab" />
    <keyboard-shortcut first-keystroke="shift ctrl meta alt equals" />
  </action>
  <action id="PreviousEditorTab">
    <keyboard-shortcut first-keystroke="shift ctrl meta alt minus" />
  </action>
  <action id="Switcher">
    <keyboard-shortcut first-keystroke="shift ctrl tab" />
  </action>
</keymap>